goodadvice_yaml_conf
